sliding_window_generator/__init__.py
sliding_window_generator/sliding_window_generator.py
sliding_window_generator-1.0.0.dist-info/LICENSE
sliding_window_generator-1.0.0.dist-info/METADATA
sliding_window_generator-1.0.0.dist-info/WHEEL
sliding_window_generator-1.0.0.dist-info/top_level.txt
sliding_window_generator-1.0.0.dist-info/RECORD
