Metadata-Version: 2.1
Name: sliding-window-generator
Version: 1.0.0
Summary: Generate Sliding Window from Time Series Dataset
Home-page: https://github.com/anencore94/SlidingWindowGenerator
Author: Jaeyeon Kim
Author-email: anencore94@gmail.com
License: UNKNOWN
Platform: UNKNOWN
Classifier: Programming Language :: Python :: 3
Classifier: License :: OSI Approved :: MIT License
Classifier: Operating System :: OS Independent
Requires-Python: >=3.6
